aioimaplib/__init__.py
aioimaplib/aioimaplib.py
aioimaplib/imap_testing_server.py
aioimaplib-2.0.0.dist-info/LICENSE.txt
aioimaplib-2.0.0.dist-info/METADATA
aioimaplib-2.0.0.dist-info/WHEEL
aioimaplib-2.0.0.dist-info/entry_points.txt
aioimaplib-2.0.0.dist-info/RECORD
