Metadata-Version: 2.1
Name: aioimaplib
Version: 2.0.0
Summary: Python asyncio IMAP4rev1 client library
Home-page: https://github.com/bamthomas/aioimaplib
License: GPL-3.0
Keywords: asyncio,mail,imap
Author: Bruno THOMAS
Author-email: bthomas@iroco.fr
Requires-Python: >=3.9,<4.0
Classifier: Intended Audience :: Developers
Classifier: License :: OSI Approved :: GNU General Public License v3 (GPLv3)
Classifier: Natural Language :: English
Classifier: Programming Language :: Python
Classifier: Programming Language :: Python :: 3
Classifier: Programming Language :: Python :: 3.9
Classifier: Programming Language :: Python :: 3.10
Classifier: Programming Language :: Python :: 3.11
Classifier: Programming Language :: Python :: 3.12
Classifier: Topic :: Communications :: Email :: Post-Office :: IMAP
Classifier: Topic :: Internet
Classifier: Topic :: Software Development :: Libraries :: Python Modules
Project-URL: Repository, https://github.com/bamthomas/aioimaplib
